expview/__init__.py
expview/__main__.py
expview/exp.py
expview/mylogs.py
expview/show.py
expview/reports/__init__.py
expview/reports/compare.py
expview/reports/latex.py
expview/utils/__init__.py
expview/utils/utils.py
expview/win/__init__.py
expview/win/colors.py
expview/win/obj_util.py
expview/win/setup.py
expview/win/win_util.py
expview-0.1.1.dist-info/METADATA
expview-0.1.1.dist-info/WHEEL
expview-0.1.1.dist-info/entry_points.txt
expview-0.1.1.dist-info/top_level.txt
expview-0.1.1.dist-info/RECORD
