Metadata-Version: 2.4
Name: expview
Version: 0.1.1
Summary: Experimental data manager and visualization tools
Author: Ahmad Pouramini
License: MIT
Project-URL: Homepage, https://github.com/puraminy/ExpView
Requires-Python: >=3.8
Requires-Dist: click>=8.0
Requires-Dist: pandas>=1.5
Requires-Dist: numpy>=1.23
Requires-Dist: matplotlib>=3.7
Requires-Dist: seaborn>=0.12
Requires-Dist: tqdm>=4.65
Requires-Dist: six>=1.16
Requires-Dist: pyperclip>=1.8
Requires-Dist: pytz>=2024.1
Requires-Dist: PyPDF2>=3.0
Requires-Dist: regex>=2023.12
Requires-Dist: Pillow>=10.0
Requires-Dist: appdirs>=1.4
Requires-Dist: debugpy>=1.8
Requires-Dist: windows-curses; platform_system == "Windows"
